{
      "Name": "TaKIPI",
      "URL": "http://hdl.handle.net/11321/31",
	"Family": "Part-of-Speech Tagging and Lemmatisation",
      "Description": "This tool assumes the morpho-syntactic description of the IPI PAN corpus tagset (Przepiórkowski <a href=\"https://www.clarin.eu/resource-families/tools-part-speech-tagging-and-lemmatization#Przepi%C3%B3rkowski%202005\">2005</a>).",
      "Functionality": ["MSD"],
      "Language": ["pol"],
      "Licence": "",
      "Platform": [],
      "Infrastructure": "CLARIN-PL",
      "Group": "For a single language",
      "Input format": [],
      "Output format": [],
      "Access": {
	"Download": ""
	},
      "Publication": ["Przepiórkowski (2005)", "Piasecki (2007)"]
}
