{
      "Name": "TreeTagger",
      "URL": "http://hdl.handle.net/11022/1007-0000-0000-8E4D-B",
	"Family": "Part-of-Speech Tagging and Lemmatisation",
      "Description": "This tool is a PoS tagger and lemmatizer implemented in WebLicht.",
      "Functionality": ["PoS", "lemma"],
      "Language": ["deu", "eng", "fra", "ita", "nld", "spa", "bul", "rus", "ell", "por", "zho", "swh", "lat", "est", "fro"],
      "Licence": "free but unspecified",
      "Infrastructure": "CLARIN-D",
      "Group": "For multiple languages",
      "Input format": [],
      "Output format": ["plain text"],
      "Access": {
	"Download": "http://hdl.handle.net/11022/1007-0000-0000-8E4D-B",
	"WebLicht": "https://weblicht.sfs.uni-tuebingen.de/weblichtwiki/index.php/Main_Page"
	},
      "Publication": "Schmid (1999)"
}
