{
      "Name": "Hertha",
      "URL": "https://spraakbanken.gu.se/eng/resource/ub-kvt-hertha#tabs=information",
	"Family": "Newspaper corpora",
      "Description": "This corpus contains articles from the newspaper <a href=\"http://www.fredrikabremer.se/tidskriften-hertha/\">Hertha</a> from 1914 to 2015.\nThe corpus is available for download from Språkbanken and can be accessed through the concordancer Korp.",
      "Language": ["swe"],
      "Licence": "CC BY",
      "Size": ["3.8 million tokens"],
      "Annotation": ["tokenized", "PoS-tagged", "parsed"],
      "Infrastructure": "CLARIN",
      "Access": {
	"Concordancer": "http://spraakbanken.gu.se/korp/?mode=all_hist#corpus=ub-kvt-hertha",
	"Download": "http://spraakbanken.gu.se/eng/resource/ub-kvt-hertha#tabs=information"
	},
      "Publication": ""
}
