{
      "Name": "Hellenic National Corpus",
      "URL": "http://hdl.grnet.gr/11500/ATHENA-0000-0000-23E2-9",
	"Family": "Reference corpora",
      "Description": "This corpus includes Greek texts published from 1990 onwards.\nThe corpus is available for online browsing through a dedicated concordancer.",
      "Languages": ["ell"],
      "License": "proprietary",
      "Size": ["47 million words"],
      "Annotation": ["sentence segmented"],
      "Infrastructure": "CLARIN",
      "Access": {
	"Concordancer": "https://hnc.ilsp.gr/index.php?current_page=main"
	},
      "Publication":"https://www.zotero.org/groups/562080/items/BFNNJIVE"
}
