{
      "Name": "CIPM - Corpus Informatizado do Português Medieval",
      "URL": "https://hdl.handle.net/21.11129/0000-000D-F934-0",
	"Family": "Historical corpora",
      "Description": "This is a corpus of historical, religious, notarial, literary texts in prose and verse.\nThe texts were written between the 9th and 16th centuries.\nThe corpus is available from PORTULAN.",
      "Language": ["por"],
      "Licence": "CC BY-NC-ND",
      "Size": ["3.5 million words"],
      "Annotation": ["tokenised", "PoS-tagged"],
      "Infrastructure": "CLARIN",
      "Access": {
	"Browse": "https://cipm.fcsh.unl.pt/",
	"Download": "https://hdl.handle.net/21.11129/0000-000D-F934-0"
	},
      "Publication":""
}
